hardware/d_mem.v
module d_mem #(parameter SIZE = 256) (
    input [31:0] Address,
    input [31:0] WriteData,
    input MemWrite,
    input MemRead,
    output [31:0] ReadData
);

reg [31:0] ram [0:SIZE-1];

always @(*) begin
        if (MemWrite) begin
            ram[Address >> 2] = WriteData;
        end
    end

assign ReadData = (MemRead) ? ram[Address >> 2] : 32'bz;

endmodule

hardware/ula.v
module ula(
    input [31:0] in1,
    input [31:0] in2,
    input [3:0] op,
    output [31:0] result,
    output zero_flag,
);

@always @ * begin

case (op)
    4'b0000: result = in1 + in2; // Adição
    4'b0001: result = in1 - in2; // Subtração
    4'b0010: result = in1 & in2; // AND (E)
    4'b0011: result = int1 | in2;// OR (OU)
    4'b0100: result = in1 ^ in2; // XOR
    4'b0101: result = ~(in1 | in2); // Nor

    // Operadores Shift
    4'b0110: result = in2 << in1[4:0]; // shift left lógico (sll) / sllv (sll varável)
    4'b0111: result = in2 >> in1[4:0]; // srl / srlv (sem sinal)
    4'b1000: result = $signed(in2) >>> in1[4:0]; // sra / srav (com sinal)

    // Comparações
    4'b1001: result = ($signed(in1) < $signed(in2)) ? 32'd1 : 32'd0; // signed menor que
    4'b1010: result = (in1 < in2) ? 32'd1 : 32'd0; // unsigned menor que

    4'b1011: result = in2;
    4'b1100: result = in1;

    //OBS: Ainda sobraram alguns bits para fazer outras operações caso necessário
    default: result = 32'b0;
endcase

    if (result == 0) begin
        zero_flag <= 1'b0;
    end
end

endmodule

hardware/ula_ctrl.v
module ula_ctrl (
    input [3:0] ALUOp,
    input [5:0] Funct,
    output reg [3:0] ula_OP
);

    always @(*) begin
        case (ALUOp)
            4'b0000: begin
                case (Funct)
                    6'b100000: ula_OP = 4'b0000;
                    6'b100010: ula_OP = 4'b0001;
                    6'b100100: ula_OP = 4'b0010; 
                    6'b100101: ula_OP = 4'b0011;
                    6'b100110: ula_OP = 4'b0100; 
                    6'b100111: ula_OP = 4'b0101;
                    6'b101010: ula_OP = 4'b1001; 
                    6'b101011: ula_OP = 4'b1010; 
                    
                    // Operações de Shift
                    6'b000000: ula_OP = 4'b0110;
                    6'b000010: ula_OP = 4'b0111;
                    6'b000011: ula_OP = 4'b1000;
                    6'b000111: ula_OP = 4'b1000; 
                    6'b000100: ula_OP = 4'b0110;
                    6'b000110: ula_OP = 4'b0111;
                    
                    default:   ula_OP = 4'b0000;
                endcase
            end

            
            4'b0001: ula_OP = 4'b0000; 
            4'b0010: ula_OP = 4'b0001; 
            4'b0011: ula_OP = 4'b0010; 
            4'b0100: ula_OP = 4'b0011; 
            4'b0101: ula_OP = 4'b0100;
            4'b0110: ula_OP = 4'b1001;
            4'b0111: ula_OP = 4'b1010;
            4'b1000: ula_OP = 4'b1011;
            
            default: ula_OP = 4'b0000;
        endcase
    end
endmodule

hardware/regfile.v
module regfile(
    input clock,
    input regWrite,
    input reset,
    input [4:0] readAddr1,
    input [4:0] readAddr2,
    input [4:0] writeAddr,
    input [31:0] writeData,
    output [31:0] readData1,
    output [31:0] readData2
);

reg [31:0] registers [0:31];
integer i;

always @(posedge clock) begin
        if (reset) begin
            for (i = 0; i < 32; i = i + 1) begin
                registers[i] <= 32'h00000000;
            end
        end else if (regWrite) begin
            if (writeAddr != 5'd0) begin
                registers[writeAddr] <= writeData;
            end
        end
    end


assign readData1 = (readAddr1 == 5'd0) ? 32'd0 : registers[readAddr1];
assign readData2 = (readAddr2 == 5'd0) ? 32'd0 : registers[readAddr2];

endmodule

hardware/ctrl.v
module ctrl (
    input wire [5:0] Opcode,
    output reg [1:0] RegDst,
    output reg ALUSrc,
    output reg [1:0] MemtoReg,
    output reg RegWrite,
    output reg MemRead,
    output reg MemWrite,
    output reg Branch,
    output reg Bne,
    output reg Jump,
    output reg [3:0] ALUOp
);

    always @(*) begin
        RegDst   = 2'b00;
        ALUSrc   = 1'b0;
        MemtoReg = 2'b00;
        RegWrite = 1'b0;
        MemRead  = 1'b0;
        MemWrite = 1'b0;
        Branch   = 1'b0;
        Bne      = 1'b0;
        Jump     = 1'b0;
        ALUOp    = 4'b0000;

        case (Opcode)
            6'b000000: begin
                RegDst   = 2'b01;
                RegWrite = 1'b1;
                ALUOp    = 4'b0000;
            end

            6'b000010: begin
                Jump = 1'b1;
            end

            6'b000011: begin
                Jump     = 1'b1;
                RegWrite = 1'b1;
                RegDst   = 2'b10; 
                MemtoReg = 2'b10;
            end

            6'b000100: begin
                Branch = 1'b1;
                ALUOp  = 4'b0010;
            end

            6'b000101: begin
                Bne   = 1'b1;
                ALUOp = 4'b0010;
            end

            6'b001000: begin
                ALUSrc   = 1'b1;
                RegWrite = 1'b1;
                ALUOp    = 4'b0001; 
            end

            6'b001010: begin
                ALUSrc   = 1'b1;
                RegWrite = 1'b1;
                ALUOp    = 4'b0110; 
            end

            6'b001011: begin
                ALUSrc   = 1'b1;
                RegWrite = 1'b1;
                ALUOp    = 4'b0111; 
            end

            6'b001100: begin
                ALUSrc   = 1'b1;
                RegWrite = 1'b1;
                ALUOp    = 4'b0011;
            end

            6'b001101: begin
                ALUSrc   = 1'b1;
                RegWrite = 1'b1;
                ALUOp    = 4'b0100;
            end

    
            6'b001110: begin
                ALUSrc   = 1'b1;
                RegWrite = 1'b1;
                ALUOp    = 4'b0101; 
            end

            6'b001111: begin
                ALUSrc   = 1'b1;
                RegWrite = 1'b1;
                ALUOp    = 4'b1000; 
            end

    
            6'b100011: begin
                ALUSrc   = 1'b1;
                MemtoReg = 2'b01; 
                RegWrite = 1'b1;
                MemRead  = 1'b1;
                ALUOp    = 4'b0001; 
            end

            6'b101011: begin
                ALUSrc   = 1'b1;
                MemWrite = 1'b1;
                ALUOp    = 4'b0001; 
            end
        endcase
    end
endmodule

hardware/i_mem.v
module i_mem #(parameter SIZE = 256)(
    input [31:0] address,
    output [31:0] i_out
);

reg [31:0] rom  [0:SIZE - 1];

initial begin
    $readmemb("instruction.list.v", rom);
end

assign i_out = rom[address >> 2];   

endmodule

hardware/pc.v
module pc (
    input wire clock,
    input [31:0] nextpc, //vem do somador_pc
    output reg [31:0] pc
);

//garante que o PC começa em zero
initial begin
    pc = 32'h00000000;
end

always @(posedge clock) begin
    pc <= nextpc;
end

endmodule

hardware/top.v
module top (
    input wire clock,
    input wire reset,
    output wire [31:0] PC_out,
    output wire [31:0] ULA_out,
    output wire [31:0] DMem_out
);

    wire [31:0] pc_atual, next_pc, pc_mais_4;
    wire [31:0] instruction;
    
    wire [1:0] RegDst, MemtoReg;
    wire ALUSrc, RegWrite, MemRead, MemWrite, Branch, Bne, Jump;
    wire [3:0] ALUOp;
    
    wire [4:0] write_reg_addr;
    wire [31:0] write_data, read_data1, read_data2;
    
    wire [3:0] ula_op_final;
    wire [31:0] alu_in2, alu_result;
    wire zero_flag;
    
    wire [31:0] read_data_mem;
    
    wire [31:0] sign_ext_imm, shifted_imm, branch_target, jump_target;
    wire branch_taken;

    assign PC_out = pc_atual;
    assign ULA_out = alu_result;
    assign DMem_out = read_data_mem;

    assign pc_mais_4 = pc_atual + 32'd4;
    
    assign sign_ext_imm = {{16{instruction[15]}}, instruction[15:0]};
    assign shifted_imm = sign_ext_imm << 2;
    
    assign branch_target = pc_mais_4 + shifted_imm;
    assign jump_target = {pc_mais_4[31:28], instruction[25:0], 2'b00};
    
    assign branch_taken = (Branch & zero_flag) | (Bne & ~zero_flag);
    assign next_pc = Jump ? jump_target : (branch_taken ? branch_target : pc_mais_4);
    
    assign write_reg_addr = (RegDst == 2'b01) ? instruction[15:11] : 
                            (RegDst == 2'b10) ? 5'd31 : instruction[20:16];
                            
    assign alu_in2 = ALUSrc ? sign_ext_imm : read_data2;
    
    assign write_data = (MemtoReg == 2'b01) ? read_data_mem : 
                        (MemtoReg == 2'b10) ? pc_mais_4 : alu_result;

    pc meu_pc (
        .clock(clock),
        .nextpc(next_pc),
        .pc(pc_atual)
    );

    i_mem minha_mem_instrucao (
        .address(pc_atual),
        .i_out(instruction)
    );

    ctrl minha_unidade_controlo (
        .Opcode(instruction[31:26]),
        .RegDst(RegDst),
        .ALUSrc(ALUSrc),
        .MemtoReg(MemtoReg),
        .RegWrite(RegWrite),
        .MemRead(MemRead),
        .MemWrite(MemWrite),
        .Branch(Branch),
        .Bne(Bne),
        .Jump(Jump),
        .ALUOp(ALUOp)
    );

    regfile meu_banco_registradores (
        .clock(clock),
        .regWrite(RegWrite),
        .reset(reset),
        .readAddr1(instruction[25:21]),
        .readAddr2(instruction[20:16]),
        .writeAddr(write_reg_addr),
        .writeData(write_data),
        .readData1(read_data1),
        .readData2(read_data2)
    );

    ula_ctrl meu_controlo_ula (
        .ALUOp(ALUOp),
        .Funct(instruction[5:0]),
        .ula_OP(ula_op_final)
    );

    ula minha_ula (
        .in1(read_data1),
        .in2(alu_in2),
        .op(ula_op_final),
        .result(alu_result),
        .zero_flag(zero_flag)
    );

    d_mem minha_mem_dados (
        .Address(alu_result),
        .WriteData(read_data2),
        .MemWrite(MemWrite),
        .MemRead(MemRead),
        .ReadData(read_data_mem)
    );

endmodule

testbench.v
`timescale 1ns / 1ps

module testbench;

    reg clock;
    reg reset;

    wire [31:0] PC_out;
    wire [31:0] ULA_out;
    wire [31:0] DMem_out;

    top meu_mips (
        .clock(clock),
        .reset(reset),
        .PC_out(PC_out),
        .ULA_out(ULA_out),
        .DMem_out(DMem_out)
    );

    always #5 clock = ~clock;

    initial begin
        $dumpfile("dump.vcd");
        $dumpvars(0, testbench);

        clock = 0;
        reset = 1;

        #10 reset = 0;
        #100;
        
        $display("Simulação concluída.");
        $finish;
    end

    always @(PC_out) begin
        $display("Tempo=%0t | PC=%0d | Saida ULA=%0d | Saida Memoria=%0d", 
                 $time, PC_out, ULA_out, DMem_out);
    end

endmodule

dump.vcd
$date
	Mon Jun 15 23:57:15 2026
$end
$version
	Icarus Verilog
$end
$timescale
	1ps
$end
$scope module testbench $end
$var wire 32 ! ULA_out [31:0] $end
$var wire 32 " PC_out [31:0] $end
$var wire 32 # DMem_out [31:0] $end
$var reg 1 $ clock $end
$var reg 1 % reset $end
$scope module meu_mips $end
$var wire 32 & DMem_out [31:0] $end
$var wire 32 ' PC_out [31:0] $end
$var wire 32 ( ULA_out [31:0] $end
$var wire 1 ) branch_taken $end
$var wire 1 $ clock $end
$var wire 1 % reset $end
$var wire 1 * zero_flag $end
$var wire 5 + write_reg_addr [4:0] $end
$var wire 32 , write_data [31:0] $end
$var wire 4 - ula_op_final [3:0] $end
$var wire 32 . sign_ext_imm [31:0] $end
$var wire 32 / shifted_imm [31:0] $end
$var wire 32 0 read_data_mem [31:0] $end
$var wire 32 1 read_data2 [31:0] $end
$var wire 32 2 read_data1 [31:0] $end
$var wire 32 3 pc_mais_4 [31:0] $end
$var wire 32 4 pc_atual [31:0] $end
$var wire 32 5 next_pc [31:0] $end
$var wire 32 6 jump_target [31:0] $end
$var wire 32 7 instruction [31:0] $end
$var wire 32 8 branch_target [31:0] $end
$var wire 32 9 alu_result [31:0] $end
$var wire 32 : alu_in2 [31:0] $end
$var wire 1 ; RegWrite $end
$var wire 2 < RegDst [1:0] $end
$var wire 2 = MemtoReg [1:0] $end
$var wire 1 > MemWrite $end
$var wire 1 ? MemRead $end
$var wire 1 @ Jump $end
$var wire 1 A Branch $end
$var wire 1 B Bne $end
$var wire 1 C ALUSrc $end
$var wire 4 D ALUOp [3:0] $end
$scope module meu_banco_registradores $end
$var wire 1 $ clock $end
$var wire 5 E readAddr1 [4:0] $end
$var wire 5 F readAddr2 [4:0] $end
$var wire 1 % reset $end
$var wire 5 G writeAddr [4:0] $end
$var wire 32 H writeData [31:0] $end
$var wire 1 ; regWrite $end
$var wire 32 I readData2 [31:0] $end
$var wire 32 J readData1 [31:0] $end
$var integer 32 K i [31:0] $end
$upscope $end
$scope module meu_controlo_ula $end
$var wire 6 L Funct [5:0] $end
$var wire 4 M ALUOp [3:0] $end
$var reg 4 N ula_OP [3:0] $end
$upscope $end
$scope module meu_pc $end
$var wire 1 $ clock $end
$var wire 32 O nextpc [31:0] $end
$var reg 32 P pc [31:0] $end
$upscope $end
$scope module minha_mem_dados $end
$var wire 32 Q WriteData [31:0] $end
$var wire 32 R ReadData [31:0] $end
$var wire 1 > MemWrite $end
$var wire 1 ? MemRead $end
$var wire 32 S Address [31:0] $end
$var parameter 32 T SIZE $end
$upscope $end
$scope module minha_mem_instrucao $end
$var wire 32 U address [31:0] $end
$var wire 32 V i_out [31:0] $end
$var parameter 32 W SIZE $end
$upscope $end
$scope module minha_ula $end
$var wire 32 X in1 [31:0] $end
$var wire 32 Y in2 [31:0] $end
$var wire 4 Z op [3:0] $end
$var reg 32 [ result [31:0] $end
$var reg 1 * zero_flag $end
$upscope $end
$scope module minha_unidade_controlo $end
$var wire 6 \ Opcode [5:0] $end
$var reg 4 ] ALUOp [3:0] $end
$var reg 1 C ALUSrc $end
$var reg 1 B Bne $end
$var reg 1 A Branch $end
$var reg 1 @ Jump $end
$var reg 1 ? MemRead $end
$var reg 1 > MemWrite $end
$var reg 2 ^ MemtoReg [1:0] $end
$var reg 2 _ RegDst [1:0] $end
$var reg 1 ; RegWrite $end
$upscope $end
$upscope $end
$upscope $end
$enddefinitions $end
$comment Show the parameter values. $end
$dumpall
b100000000 W
b100000000 T
$end
#0
$dumpvars
b0 _
b0 ^
b1 ]
b1000 \
b101 [
b0 Z
b101 Y
b0 X
b100000000100010000000000000101 V
b0 U
b101 S
bz R
bx Q
b0 P
b100 O
b0 N
b1 M
b101 L
bx K
b0 J
bx I
b101 H
b10001 G
b10001 F
b0 E
b1 D
1C
0B
0A
0@
0?
0>
b0 =
b0 <
1;
b101 :
b101 9
b11000 8
b100000000100010000000000000101 7
b10001000000000000010100 6
b100 5
b0 4
b100 3
b0 2
bx 1
bz 0
b10100 /
b101 .
b0 -
b101 ,
b10001 +
0*
0)
b101 (
b0 '
bz &
1%
0$
bz #
b0 "
b101 !
$end
#5000
b10010 +
b10010 G
b10010000000000000010100 6
b10010 F
b100000000100100000000000000101 7
b100000000100100000000000000101 V
b1000 5
b1000 O
b0 1
b0 I
b0 Q
b11100 8
b1000 3
b100 "
b100 '
b100 4
b100 P
b100 U
b100000 K
1$
#10000
0$
0%
#15000
b11111111111111111111111111111101 ,
b11111111111111111111111111111101 H
b11111111111111111111111111110100 /
b11111111111111111111111111111101 !
b11111111111111111111111111111101 (
b11111111111111111111111111111101 9
b11111111111111111111111111111101 S
b11111111111111111111111111111101 [
b10100 +
b10100 G
b11111111111111111111111111111101 :
b11111111111111111111111111111101 Y
b10100111111111111110100 6
b11111111111111111111111111111101 .
b111101 L
b10100 F
b100000000101001111111111111101 7
b100000000101001111111111111101 V
b1100 5
b1100 O
b0 1
b0 I
b0 Q
b0 8
b1100 3
b1000 "
b1000 '
b1000 4
b1000 P
b1000 U
1$
#20000
0$
#25000
b11111111111111111111111111111011 ,
b11111111111111111111111111111011 H
b11111111111111111111111111101100 /
b11111111111111111111111111111011 !
b11111111111111111111111111111011 (
b11111111111111111111111111111011 9
b11111111111111111111111111111011 S
b11111111111111111111111111111011 [
b10101 +
b10101 G
b11111111111111111111111111111011 :
b11111111111111111111111111111011 Y
b10101111111111111101100 6
b11111111111111111111111111111011 .
b111011 L
b10101 F
b100000000101011111111111111011 7
b100000000101011111111111111011 V
b10000 5
b10000 O
b0 1
b0 I
b0 Q
b11111111111111111111111111111100 8
b10000 3
b1100 "
b1100 '
b1100 4
b1100 P
b1100 U
1$
#30000
0$
#35000
b1010 ,
b1010 H
b101000 /
b1010 !
b1010 (
b1010 9
b1010 S
b1010 [
b10111 +
b10111 G
b1010 :
b1010 Y
b10111000000000000101000 6
b1010 .
b1010 L
b10111 F
b100000000101110000000000001010 7
b100000000101110000000000001010 V
b10100 5
b10100 O
b0 1
b0 I
b0 Q
b111100 8
b10100 3
b10000 "
b10000 '
b10000 4
b10000 P
b10000 U
1$
#40000
0$
#45000
b111111111111111 ,
b111111111111111 H
b11111111111111100 /
b111111111111111 !
b111111111111111 (
b111111111111111 9
b111111111111111 S
b111111111111111 [
b11000 +
b11000 G
b111111111111111 :
b111111111111111 Y
b11000011111111111111100 6
b111111111111111 .
b111111 L
b11000 F
b100000000110000111111111111111 7
b100000000110000111111111111111 V
b11000 5
b11000 O
b0 1
b0 I
b0 Q
b100000000000010100 8
b11000 3
b10100 "
b10100 '
b10100 4
b10100 P
b10100 U
1$
#50000
0$
#55000
b11111111111111111000000000000000 ,
b11111111111111111000000000000000 H
b11111111111111100000000000000000 /
b11111111111111111000000000000000 !
b11111111111111111000000000000000 (
b11111111111111111000000000000000 9
b11111111111111111000000000000000 S
b11111111111111111000000000000000 [
b11001 +
b11001 G
b11111111111111111000000000000000 :
b11111111111111111000000000000000 Y
b11001100000000000000000 6
b11111111111111111000000000000000 .
b0 L
b11001 F
b100000000110011000000000000000 7
b100000000110011000000000000000 V
b11100 5
b11100 O
b0 1
b0 I
b0 Q
b11111111111111100000000000011100 8
b11100 3
b11000 "
b11000 '
b11000 4
b11000 P
b11000 U
1$
#60000
0$
#65000
b11111111111111111111111111111111 ,
b11111111111111111111111111111111 H
b11111111111111111111111111111100 /
b11111111111111111111111111111111 !
b11111111111111111111111111111111 (
b11111111111111111111111111111111 9
b11111111111111111111111111111111 S
b11111111111111111111111111111111 [
b1001 +
b1001 G
b11111111111111111111111111111111 :
b11111111111111111111111111111111 Y
b1001111111111111111100 6
b11111111111111111111111111111111 .
b111111 L
b1001 F
b100000000010011111111111111111 7
b100000000010011111111111111111 V
b100000 5
b100000 O
b0 1
b0 I
b0 Q
b11100 8
b100000 3
b11100 "
b11100 '
b11100 4
b11100 P
b11100 U
1$
#70000
0$
#75000
b111111111111111 ,
b111111111111111 H
b11111111111111100 /
b111111111111111 !
b111111111111111 (
b111111111111111 9
b111111111111111 S
b111111111111111 [
b1010 +
b1010 G
b111111111111111 :
b111111111111111 Y
b1010011111111111111100 6
b111111111111111 .
b1010 F
b100000000010100111111111111111 7
b100000000010100111111111111111 V
b100100 5
b100100 O
b0 1
b0 I
b0 Q
b100000000000100000 8
b100100 3
b100000 "
b100000 '
b100000 4
b100000 P
b100000 U
1$
#80000
0$
#85000
b100 ,
b100 H
b10000 /
b100 !
b100 (
b100 9
b100 S
b100 [
b1011 +
b1011 G
b100 :
b100 Y
b1011000000000000010000 6
b100 .
b100 L
b1011 F
b100000000010110000000000000100 7
b100000000010110000000000000100 V
b101000 5
b101000 O
b0 1
b0 I
b0 Q
b111000 8
b101000 3
b100100 "
b100100 '
b100100 4
b100100 P
b100100 U
1$
#90000
0$
#95000
b1000 ,
b1000 H
b100000 /
b1000 !
b1000 (
b1000 9
b1000 S
b1000 [
b1100 +
b1100 G
b1000 :
b1000 Y
b1100000000000000100000 6
b1000 .
b1000 L
b1100 F
b100000000011000000000000001000 7
b100000000011000000000000001000 V
b101100 5
b101100 O
b0 1
b0 I
b0 Q
b1001100 8
b101100 3
b101000 "
b101000 '
b101000 4
b101000 P
b101000 U
1$
#100000
0$
#105000
b11111111111111111111111111111000 ,
b11111111111111111111111111111000 H
b11111111111111111111111111100000 /
b11111111111111111111111111111000 !
b11111111111111111111111111111000 (
b11111111111111111111111111111000 9
b11111111111111111111111111111000 S
b11111111111111111111111111111000 [
b1101 +
b1101 G
b11111111111111111111111111111000 :
b11111111111111111111111111111000 Y
b1101111111111111100000 6
b11111111111111111111111111111000 .
b111000 L
b1101 F
b100000000011011111111111111000 7
b100000000011011111111111111000 V
b110000 5
b110000 O
b0 1
b0 I
b0 Q
b10000 8
b110000 3
b101100 "
b101100 '
b101100 4
b101100 P
b101100 U
1$
