hardware/ula.v
module ula(
    input [31:0] in1,
    input [31:0] in2,
    input [3:0] op,
    output reg [31:0] result,
    output reg zero_flag
);

always @(*) begin
result = 32'b0;
zero_flag = 1'b0;

case (op)
    4'b0000: result = in1 + in2; // Adição
    4'b0001: result = in1 - in2; // Subtração
    4'b0010: result = in1 & in2; // AND (E)
    4'b0011: result = in1 | in2;// OR (OU)
    4'b0100: result = in1 ^ in2; // XOR
    4'b0101: result = ~(in1 | in2); // Nor

    // Operadores Shift
    4'b0110: result = in2 << in1[4:0]; // shift left lógico (sll) / sllv (sll varável)
    4'b0111: result = in2 >> in1[4:0]; // srl / srlv (sem sinal)
    4'b1000: result = $signed(in2) >>> in1[4:0]; // sra / srav (com sinal)

    // Comparações
    4'b1001: result = ($signed(in1) < $signed(in2)) ? 32'd1 : 32'd0; // signed menor que
    4'b1010: result = (in1 < in2) ? 32'd1 : 32'd0; // unsigned menor que

    4'b1011: result = in2;
    4'b1100: result = in1;

    //OBS: Ainda sobraram alguns bits para fazer outras operações caso necessário
    default: result = 32'b0;
endcase

    if (result == 0) begin
        zero_flag = 1'b1;
    end else
        zero_flag = 1'b0;
    end

endmodule

tests/ula_tb.v
`timescale 1ns / 1ps // Padroniza o tempo da simulação <unidade de tempo>/<precisão do tempo>
// Logo #10 é 10ns de espera com 1ps de precisão
// É usado para simular o clock na ula
module ula_tb;

    reg  [31:0] in1, in2;
    reg  [3:0]  op;
    wire [31:0] result;
    wire        zero_flag;

    ula uut (.in1(in1), .in2(in2), .op(op), .result(result), .zero_flag(zero_flag)); // instânciando a ula

    integer passou, falhou;

    // Função para o benchmark dos testes
    task testar;
        input [3:0]  t_op;
        input [31:0] t_in1, t_in2, t_esperado;
        input        t_zero;
        begin
            op = t_op; in1 = t_in1; in2 = t_in2;
            #10;
            if (result === t_esperado && zero_flag === t_zero) begin
                $display("PASS | op=%b in1=%h in2=%h | result=%h", t_op, t_in1, t_in2, result);
                passou = passou + 1;
            end else begin
                $display("FAIL | op=%b in1=%h in2=%h | esp=%h got=%h | zero esp=%b got=%b",
                    t_op, t_in1, t_in2, t_esperado, result, t_zero, zero_flag);
                falhou = falhou + 1;
            end
        end
    endtask


    initial begin
        $dumpfile("tests/out/ula_tb.vcd"); // Especifica o caminho do executável para a simulação
        $dumpvars(0, ula_tb);   // Usa as variáveis deste módulo
        passou = 0; falhou = 0;

        $display("=== Iniciando testes da ULA ===");

        // Adição
        testar(4'b0000, 32'd15,      32'd10,      32'd25,       0); // 15+10=25 zero_flag=0
        testar(4'b0000, 32'd0,       32'd0,       32'd0,        1); // 0 + 0=0 zero_flag=1
        testar(4'b0000, 32'hFFFFFFFF,32'd1,       32'd0,        1); // -MAX+1=0 zero_flag=1
        // Subtração
        testar(4'b0001, 32'd20,      32'd8,       32'd12,       0); // 20-8=12 zero_flag=0
        testar(4'b0001, 32'd5,       32'd5,       32'd0,        1); // 5-5=0 zero_flag=1
        // AND
        testar(4'b0010, 32'hFF00FF00,32'hF0F0F0F0,32'hF000F000, 0); // mantém somente os bits iguais, zero_flag=0
        testar(4'b0010, 32'hAAAAAAAA,32'h55555555,32'd0,        1); // tudo diferente, zero_flag=1
        // OR
        testar(4'b0011, 32'hFF000000,32'h00FF0000,32'hFFFF0000, 0); // mantém bits com 1, zero_flag=0
        // XOR
        testar(4'b0100, 32'hFFFFFFFF,32'hFFFFFFFF,32'd0,        1); // 1 somente com bits diferentes, zero_flag=1
        // NOR
        testar(4'b0101, 32'h00000000,32'h00000000,32'hFFFFFFFF, 0); // 0 NOR 0 = tudo 1, zero_flag=0
        testar(4'b0101, 32'hFFFFFFFF,32'h00000000,32'h00000000, 1); // 1 NOR 0 = 0, zero_flag=1
        // SLL
        testar(4'b0110, 32'd4,       32'd1,       32'd16,       0); // 4 << 1 = 4*2 = 16 (shift com zeros à direita)
        testar(4'b0110, 32'd0,       32'd99,      32'd99,       0); // 0 << 99 = 0 (shift 0 posições), zero_flag=0
        // SRL (lógico)
        testar(4'b0111, 32'd4,       32'd16,      32'd1,        0); // 16 >> 4 = 1 (shift lógico com zeros à esquerda)
        testar(4'b0111, 32'd1,       32'hFFFFFFFF,32'h7FFFFFFF, 0); // MAX >> 1 = MAX/2 com zero a esquerda, zero_flag=0
        // SRA (aritmético)
        testar(4'b1000, 32'd1,       32'hFFFFFFFF,32'hFFFFFFFF, 0); // -1 >> 1 = -1 (propaga sinal), zero_flag=0
        testar(4'b1000, 32'd1,       32'd16,      32'd8,        0); // 16 >> 1 = 8 (shift aritmético), zero_flag=0
        // SLT
        testar(4'b1001, 32'd3,       32'd7,       32'd1,        0); // 3 < 7 = 1 (verdadeiro), zero_flag=0
        testar(4'b1001, 32'd7,       32'd3,       32'd0,        1); // 7 < 3 = 0 (falso), zero_flag=1
        testar(4'b1001, 32'hFFFFFFFF,32'd1,       32'd1,        0); // -1 < 1 = 1 (comparação com sinal), zero_flag=0
        // SLTU
        testar(4'b1010, 32'hFFFFFFFF,32'd1,       32'd0,        1); // MAX < 1 = 0 sem sinal, zero_flag=1
        testar(4'b1010, 32'd1,       32'hFFFFFFFF,32'd1,        0); // 1 < MAX = 1 sem sinal, zero_flag=0
        // LUI
        testar(4'b1011, 32'd0,       32'hABCD0000,32'hABCD0000, 0); // LUI carrega in2 como resultado, zero_flag=0

        $display("=== %0d passou, %0d falhou ===", passou, falhou);
        $finish;
    end

endmodule

tests/out/ula_tb.vcd
$date
	Wed Jun  3 11:25:07 2026
$end
$version
	Icarus Verilog
$end
$timescale
	1ps
$end
$scope module ula_tb $end
$var wire 1 ! zero_flag $end
$var wire 32 " result [31:0] $end
$var reg 32 # in1 [31:0] $end
$var reg 32 $ in2 [31:0] $end
$var reg 4 % op [3:0] $end
$var integer 32 & falhou [31:0] $end
$var integer 32 ' passou [31:0] $end
$scope module uut $end
$var wire 32 ( in1 [31:0] $end
$var wire 32 ) in2 [31:0] $end
$var wire 4 * op [3:0] $end
$var reg 32 + result [31:0] $end
$var reg 1 ! zero_flag $end
$upscope $end
$scope task testar $end
$var reg 32 , t_esperado [31:0] $end
$var reg 32 - t_in1 [31:0] $end
$var reg 32 . t_in2 [31:0] $end
$var reg 4 / t_op [3:0] $end
$var reg 1 0 t_zero $end
$upscope $end
$upscope $end
$enddefinitions $end
$comment Show the parameter values. $end
$dumpall
$end
#0
$dumpvars
00
b0 /
b1010 .
b1111 -
b11001 ,
b11001 +
b0 *
b1010 )
b1111 (
b0 '
b0 &
b0 %
b1010 $
b1111 #
b11001 "
0!
$end
#10000
1!
b0 "
b0 +
b0 $
b0 )
b0 #
b0 (
10
b0 ,
b0 .
b0 -
b1 '
#20000
1!
b1 $
b1 )
b11111111111111111111111111111111 #
b11111111111111111111111111111111 (
b1 .
b11111111111111111111111111111111 -
b10 '
#30000
b1100 "
b1100 +
0!
b1000 $
b1000 )
b10100 #
b10100 (
b1 %
b1 *
00
b1100 ,
b1000 .
b10100 -
b1 /
b11 '
#40000
1!
b0 "
b0 +
b101 $
b101 )
b101 #
b101 (
10
b0 ,
b101 .
b101 -
b100 '
#50000
b11110000000000001111000000000000 "
b11110000000000001111000000000000 +
0!
b11110000111100001111000011110000 $
b11110000111100001111000011110000 )
b11111111000000001111111100000000 #
b11111111000000001111111100000000 (
b10 %
b10 *
00
b11110000000000001111000000000000 ,
b11110000111100001111000011110000 .
b11111111000000001111111100000000 -
b10 /
b101 '
#60000
1!
b0 "
b0 +
b1010101010101010101010101010101 $
b1010101010101010101010101010101 )
b10101010101010101010101010101010 #
b10101010101010101010101010101010 (
10
b0 ,
b1010101010101010101010101010101 .
b10101010101010101010101010101010 -
b110 '
#70000
b11111111111111110000000000000000 "
b11111111111111110000000000000000 +
0!
b111111110000000000000000 $
b111111110000000000000000 )
b11111111000000000000000000000000 #
b11111111000000000000000000000000 (
b11 %
b11 *
00
b11111111111111110000000000000000 ,
b111111110000000000000000 .
b11111111000000000000000000000000 -
b11 /
b111 '
#80000
1!
b0 "
b0 +
b11111111111111111111111111111111 $
b11111111111111111111111111111111 )
b11111111111111111111111111111111 #
b11111111111111111111111111111111 (
b100 %
b100 *
10
b0 ,
b11111111111111111111111111111111 .
b11111111111111111111111111111111 -
b100 /
b1000 '
#90000
b11111111111111111111111111111111 "
b11111111111111111111111111111111 +
0!
b0 $
b0 )
b0 #
b0 (
b101 %
b101 *
00
b11111111111111111111111111111111 ,
b0 .
b0 -
b101 /
b1001 '
#100000
1!
b0 "
b0 +
b11111111111111111111111111111111 #
b11111111111111111111111111111111 (
10
b0 ,
b11111111111111111111111111111111 -
b1010 '
#110000
b10000 "
b10000 +
0!
b1 $
b1 )
b100 #
b100 (
b110 %
b110 *
00
b10000 ,
b1 .
b100 -
b110 /
b1011 '
#120000
b1100011 "
b1100011 +
b1100011 $
b1100011 )
b0 #
b0 (
b1100011 ,
b1100011 .
b0 -
b1100 '
#130000
b1 "
b1 +
b10000 $
b10000 )
b100 #
b100 (
b111 %
b111 *
b1 ,
b10000 .
b100 -
b111 /
b1101 '
#140000
b1111111111111111111111111111111 "
b1111111111111111111111111111111 +
b11111111111111111111111111111111 $
b11111111111111111111111111111111 )
b1 #
b1 (
b1111111111111111111111111111111 ,
b11111111111111111111111111111111 .
b1 -
b1110 '
#150000
b11111111111111111111111111111111 "
b11111111111111111111111111111111 +
b1000 %
b1000 *
b11111111111111111111111111111111 ,
b1000 /
b1111 '
#160000
b1000 "
b1000 +
b10000 $
b10000 )
b1000 ,
b10000 .
b10000 '
#170000
b1 "
b1 +
b111 $
b111 )
b11 #
b11 (
b1001 %
b1001 *
b1 ,
b111 .
b11 -
b1001 /
b10001 '
#180000
1!
b0 "
b0 +
b11 $
b11 )
b111 #
b111 (
10
b0 ,
b11 .
b111 -
b10010 '
#190000
b1 "
b1 +
0!
b1 $
b1 )
b11111111111111111111111111111111 #
b11111111111111111111111111111111 (
00
b1 ,
b1 .
b11111111111111111111111111111111 -
b10011 '
#200000
1!
b0 "
b0 +
b1010 %
b1010 *
10
b0 ,
b1010 /
b10100 '
#210000
b1 "
b1 +
0!
b11111111111111111111111111111111 $
b11111111111111111111111111111111 )
b1 #
b1 (
00
b1 ,
b11111111111111111111111111111111 .
b1 -
b10101 '
#220000
b10101011110011010000000000000000 "
b10101011110011010000000000000000 +
b10101011110011010000000000000000 $
b10101011110011010000000000000000 )
b0 #
b0 (
b1011 %
b1011 *
b10101011110011010000000000000000 ,
b10101011110011010000000000000000 .
b0 -
b1011 /
b10110 '
#230000
b10111 '
